text_label/__init__.py
text_label/bus.py
text_label/gui.py
text_label/history.py
text_label/main.py
text_label/project.py
text_label/statechart.py
text_label/text_info.py
text_label/exporters/__init__.py
text_label/exporters/text_directory.py
simple_text_label-0.0.1.1.dist-info/METADATA
simple_text_label-0.0.1.1.dist-info/WHEEL
simple_text_label-0.0.1.1.dist-info/entry_points.txt
simple_text_label-0.0.1.1.dist-info/top_level.txt
simple_text_label-0.0.1.1.dist-info/RECORD
